[
    {
      "id": "brooke",
      "name": "Brooke Monk",
      "description": "",
      "photoFolder": ["Brooke"]
    },
      {
      "id": "charlie",
      "name": "Charlie D'Amelio",
      "description": "",
      "photoFolder": ["Charli"]
    },
    {
      "id": "Dilara",
      "name": "Dilara",
      "description": "",
      "photoFolder": ["Dilara"]
    },
  
    {
      "id": "Dionisia",
      "name": "Dionisia",
      "description": "",
      "photoFolder": ["Dionisia"]
    },
    {
      "id": "Emni",
      "name": "Emni",
      "description": "",
      "photoFolder": ["Emni"]
    },
    {
      "id": "Jade Anna",
      "name": "Jade Anna",
      "description": "",
      "photoFolder": ["Jade Anna"]
    },
    {
      "id": "Laura",
      "name": "Queen Laura",
      "description": "",
      "photoFolder": ["Laura"]
    }
  ]